{
  "hero": {
    "eyebrow": "職涯需求覺察系統 · TWA",
    "title": "探索自己的工作價值觀，\n設計自己理想職涯",
    "subtitle": "我們常在工作中感到委屈、無力，甚至懷疑自己的能力。但很多時候，**這並不是你不夠優秀，而是你身處的環境，無法提供你內心真正渴望的養分**。而這份評測不是為了打分數，而是要幫你找回人生的「原味藍圖」，透過 30 分鐘的深度覺察，找到你真正重視的工作價值。",
    "ctaText": "先了解這份評測",
    "ctaTarget": "#motivation-section",
    "quote": "",
    "intro": "",
    "stats": [
      {
        "value": "20-30",
        "label": "分鐘的旅程",
        "hint": "建議在平靜的時段慢慢做，中途可暫停續寫。"
      },
      {
        "value": "6",
        "valueSmall": "+20",
        "label": "大需求類別",
        "hint": "成就、舒適、地位、利他、安全、自主 — 含 20 項環境指標。"
      },
      {
        "value": "TWA",
        "label": "工作適應理論",
        "hint": "Theory of Work Adjustment · 明尼蘇達大學 Dawis & Lofquist",
        "variant": "compact"
      }
    ]
  },
  "valueIntro": {
    "enabled": false,
    "eyebrow": "",
    "sectionTitle": "🗺️啟航之前",
    "lead": "在開始之前，讓我們先釐清三件事：",
    "footnote": null,
    "paragraphs": []
  },
  "motivation": {
    "eyebrow": "WHY THIS MATTERS",
    "sectionTitle": "這個評測對你的幫助是什麼？",
    "subtitle": "三個你一定要知道的答案，決定這 30 分鐘值不值得。",
    "cards": [
      {
        "icon": "compass",
        "tagline": "從內在出發",
        "title": "什麼是工作價值觀？它就是你的「心理需求」",
        "description": "你在職場上覺得「什麼重要、什麼不重要」—— **這些條件的存在與否，會直接決定你每天上班是感到「滿足」還是「匱乏」**，並深刻影響你的情緒起伏。\n\n如果用心理學的「工作調節理論」來解釋，工作從來不是單向的忍耐，而是一場你與職場環境的「交換」。你的價值觀，就是你內在的「心理需求」；而公司提供的薪水、成就感、自主權，則是環境給你的「強化物」。當兩者完美對上時，你才會產生真正的「工作滿意度」。",
        "emoji": "🧭"
      },
      {
        "icon": "map",
        "tagline": "探詢內在感受",
        "title": "為什麼要釐清它？看見支撐你長久發展的「底層動力」",
        "description": "你越了解自己要什麼，就越能在挑選工作時，**敏銳地判斷「這份工作究竟能不能餵養我」**。\n\n很多人找工作只看「職稱」和「薪水」，卻忽略了背後的價值觀契合度。理論指出，個人的需求與環境的資源必須達到「適配」，這段雇傭關係才能長久穩定。釐清價值觀，能幫你分出輕重緩急：找出你內在的「核心動力」，以及「為了大局可以忍受的彈性空間」。當你清楚自己的底線，就不會輕易被外界的雜音或短期的挫折給擊倒。",
        "emoji": "🌳"
      },
      {
        "icon": "anchor",
        "tagline": "化為具體條件",
        "title": "具體該怎麼用？學會「反向設計」你的面試與轉職策略",
        "description": "價值觀不是空泛的學術名詞，**它是你最強大的「面試探針」**。\n\n當你透過這份評測，把模糊的感受具體化為「環境指標」後，你就能學會 **反向設計面試問題**，主動出擊確認職場細節，而不是被動等待公司挑選。",
        "callouts": [
          {
            "label": "範例 1 · 在乎「發揮創意（自主）」",
            "text": "請問團隊對於專案執行，容錯空間有多大？如果我有新點子，通常的提案流程是什麼？"
          },
          {
            "label": "範例 2 · 無法妥協「主管挺人（安全）」",
            "text": "請問過去團隊遇到跨部門衝突或專案失誤時，主管通常會如何介入處理？"
          }
        ],
        "emoji": "🧩"
      }
    ]
  },
  "sop": {
    "eyebrow": "HOW TO USE",
    "sectionTitle": "評測怎麼進行？",
    "leadText": "評測區內所有操作，圍繞以下三個核心動作。",
    "groups": [
      {
        "label": "核心操作",
        "icon": "zap",
        "color": "teal",
        "subtitle": "在評測區裡，你會做這三件事",
        "steps": [
          {
            "icon": "sliders-horizontal",
            "title": "雙軌評分",
            "description": "同時評估「現況滿意度」與未來的「理想期待值」（0–10）。"
          },
          {
            "icon": "check-square",
            "title": "選擇指標",
            "description": "根據理想分數獲得預算：基礎 1 點、進階 2 點。Hover 任一指標可查看完整職場場景說明。",
            "highlight": true
          },
          {
            "icon": "scale",
            "title": "預算取捨",
            "description": "全站有限的 115 分預算，逼你對最在乎的項目做有意識的選擇。"
          }
        ]
      }
    ]
  },
  "prepareChecklist": {
    "eyebrow": "BEFORE YOU BEGIN",
    "sectionTitle": "開始之前，先為自己做好準備",
    "items": [
      {
        "icon": "wind",
        "title": "回到中心",
        "description": "為自己空下半小時平靜時光，讓注意力從外界雜訊回到內在。"
      },
      {
        "icon": "user-pen",
        "title": "填寫背景",
        "description": "簡短寫下目前職業與長期職涯目標，幫助系統描繪你此刻的情境。"
      }
    ]
  },
  "readyPrompt": {
    "eyebrow": "READY TO BEGIN",
    "title": "深呼吸。現在，開始向內覺察的旅程",
    "subtitle": "系統會自動幫你存檔，進度不會遺失。過程中隨時都可以暫停，晚點回來繼續。",
    "buttonText": "準備好了，開始評測",
    "footnote": "預計花費 20–30 分鐘。"
  },
  "reflection": {
    "eyebrow": "BEFORE YOU WRITE",
    "sectionTitle": "完成評測後，你會感受到過程中的成長",
    "cards": [
      {
        "icon": "shield-half",
        "tagline": "關於放下",
        "title": "犧牲與放下的勇氣",
        "description": "那些你目前給予低分的項目，是你為了守護核心價值，而在現實中展現的寬容度。學會放下，才能拿穩真正珍視的部分。",
        "emoji": "🍃"
      },
      {
        "icon": "sparkles",
        "tagline": "關於投注",
        "title": "選擇的人生哲學",
        "description": "分數就是能量預算。投注分值越高，代表你對該指標投注的注意力會更有意識的具體，獲得的回饋也會更豐富。",
        "emoji": "🌱"
      }
    ]
  },
  "insight": {
    "hint": "「完成了價值排序與評估，請自由的寫下你此刻最真實的覺察...」",
    "placeholder": "看著理想與現況的落差，帶給你什麼感受？如果現在擁有的環境資源被拿掉，你能接受嗎？或是為了縮小這個差距，你想要如何行動呢？"
  }
}
